README.md
setup.cfg
setup.py
prob_function88ruisanchez/Binomialdistribution.py
prob_function88ruisanchez/Gaussiandistribution.py
prob_function88ruisanchez/Generaldistribution.py
prob_function88ruisanchez/__init__.py
prob_function88ruisanchez.egg-info/PKG-INFO
prob_function88ruisanchez.egg-info/SOURCES.txt
prob_function88ruisanchez.egg-info/dependency_links.txt
prob_function88ruisanchez.egg-info/not-zip-safe
prob_function88ruisanchez.egg-info/top_level.txt