Metadata-Version: 1.0
Name: prob-function88ruisanchez
Version: 0.2
Summary: Gaussian distributions
Home-page: UNKNOWN
Author: UNKNOWN
Author-email: UNKNOWN
License: UNKNOWN
Platform: UNKNOWN
